cosmic_counsel/__init__.py
cosmic_counsel/__main__.py
cosmic_counsel/cosmic_utils.py
cosmic_counsel/inverted_index.py
cosmic_counsel/data/chat_history.json
cosmic_counsel/data/relevant_history.json
cosmic_counsel-0.3.18.dist-info/METADATA
cosmic_counsel-0.3.18.dist-info/WHEEL
cosmic_counsel-0.3.18.dist-info/entry_points.txt
cosmic_counsel-0.3.18.dist-info/top_level.txt
cosmic_counsel-0.3.18.dist-info/RECORD
